LICENSE
README.md
setup.py
topography/__init__.py
topography/data/__init__.py
topography/data/_models.py
topography/data/generate_dataset.py
topography/data/generate_image.py
topography/data/generate_noise.py
topography/data/generate_utils.py
topography/data/make_dataset.py
topography/data/samples/noise/0.png
topography/data/samples/noise/1.png
topography/data/samples/noise/10.png
topography/data/samples/noise/11.png
topography/data/samples/noise/12.png
topography/data/samples/noise/13.png
topography/data/samples/noise/14.png
topography/data/samples/noise/15.png
topography/data/samples/noise/16.png
topography/data/samples/noise/17.png
topography/data/samples/noise/18.png
topography/data/samples/noise/19.png
topography/data/samples/noise/2.png
topography/data/samples/noise/20.png
topography/data/samples/noise/21.png
topography/data/samples/noise/22.png
topography/data/samples/noise/23.png
topography/data/samples/noise/24.png
topography/data/samples/noise/3.png
topography/data/samples/noise/4.png
topography/data/samples/noise/5.png
topography/data/samples/noise/6.png
topography/data/samples/noise/7.png
topography/data/samples/noise/8.png
topography/data/samples/noise/9.png
topography/data/samples/raw/00000.png
topography/data/samples/raw/00001.png
topography/data/samples/raw/00002.png
topography/data/samples/raw/00003.png
topography/data/samples/raw/00004.png
topography/data/samples/raw/00005.png
topography/data/samples/raw/00006.png
topography/data/samples/raw/00007.png
topography/data/samples/raw/00008.png
topography/data/samples/raw/00009.png
topography/data/samples/raw/00010.png
topography/data/samples/raw/00011.png
topography/data/samples/raw/00012.png
topography/data/samples/raw/00013.png
topography/data/samples/raw/00014.png
topography/data/samples/raw/00015.png
topography/data/samples/raw/00016.png
topography/data/samples/raw/00017.png
topography/data/samples/raw/00018.png
topography/data/samples/raw/00019.png
topography/data/samples/raw/00020.png
topography_surface.egg-info/PKG-INFO
topography_surface.egg-info/SOURCES.txt
topography_surface.egg-info/dependency_links.txt
topography_surface.egg-info/requires.txt
topography_surface.egg-info/top_level.txt